LICENSE
MANIFEST.in
README.rst
setup.py
tox.ini
verktyg/__init__.py
verktyg/application.py
verktyg/datastructures.py
verktyg/dispatch.py
verktyg/exception_dispatch.py
verktyg/exceptions.py
verktyg/requests.py
verktyg/responses.py
verktyg/routing.py
verktyg/test.py
verktyg/urls.py
verktyg/utils.py
verktyg/views.py
verktyg/wsgi.py
verktyg.egg-info/PKG-INFO
verktyg.egg-info/SOURCES.txt
verktyg.egg-info/dependency_links.txt
verktyg.egg-info/top_level.txt
verktyg/accept/__init__.py
verktyg/accept/_base.py
verktyg/accept/charset.py
verktyg/accept/content_type.py
verktyg/accept/language.py
verktyg/http/__init__.py
verktyg/http/auth.py
verktyg/http/basic.py
verktyg/http/cache_control.py
verktyg/http/cookies.py
verktyg/testsuite/__init__.py
verktyg/testsuite/test_accept.py
verktyg/testsuite/test_accept_charset.py
verktyg/testsuite/test_accept_content_type.py
verktyg/testsuite/test_accept_language.py
verktyg/testsuite/test_application.py
verktyg/testsuite/test_datastructures.py
verktyg/testsuite/test_dispatch.py
verktyg/testsuite/test_exceptions.py
verktyg/testsuite/test_http.py
verktyg/testsuite/test_requests.py
verktyg/testsuite/test_responses.py
verktyg/testsuite/test_routing.py
verktyg/testsuite/test_urls.py
verktyg/testsuite/test_utils.py
verktyg/testsuite/test_views.py
verktyg/testsuite/test_wsgi.py
verktyg/testsuite/resources/test.txt